<skeleton name="hit_effect_42260" frameRate="24" version="2.2">
 <armatures>
  <armature name="hit_effect_42260">
   <b name="hit_effect_42260_1" x="-5" y="0" kX="0" kY="0" cX="1" cY="1" pX="0" pY="0" z="0">
    <d name="hit_effect_42260_1" pX="81.75" pY="81.75"/>
    <d name="hit_effect_42260_2" pX="81.75" pY="81.75"/>
    <d name="hit_effect_42260_4" pX="81.75" pY="81.75"/>
    <d name="hit_effect_42260_5" pX="81.75" pY="81.75"/>
    <d name="hit_effect_42260_6" pX="81.75" pY="81.75"/>
   </b>
  </armature>
 </armatures>
 <animations>
  <animation name="hit_effect_42260">
   <mov name="effect" dr="6" to="0" drTW="6" lp="0" twE="NaN">
    <b name="hit_effect_42260_1" sc="1" dl="0">
     <f x="-5" y="0" cocos2d_x="-5" cocos2d_y="0" kX="0" kY="0" cX="1" cY="1" pX="0" pY="0" z="0" dI="0" twE="NaN" tweenFrame="0" dr="1"/>
     <f x="-5" y="0" cocos2d_x="-5" cocos2d_y="0" kX="0" kY="0" cX="1" cY="1" pX="0" pY="0" z="0" dI="1" twE="NaN" tweenFrame="0" dr="1"/>
     <f x="-5" y="0" cocos2d_x="-5" cocos2d_y="0" kX="0" kY="0" cX="1" cY="1" pX="0" pY="0" z="0" dI="2" twE="NaN" tweenFrame="0" dr="1"/>
     <f x="-5" y="0" cocos2d_x="-5" cocos2d_y="0" kX="0" kY="0" cX="1" cY="1" pX="0" pY="0" z="0" dI="3" twE="NaN" tweenFrame="0" dr="1"/>
     <f x="-5" y="0" cocos2d_x="-5" cocos2d_y="0" kX="0" kY="0" cX="1" cY="1" pX="0" pY="0" z="0" dI="4" twE="NaN" tweenFrame="0" dr="1"/>
     <f dr="1" dI="-1"/>
    </b>
   </mov>
  </animation>
 </animations>
 <TextureAtlas name="hit_effect_42260" width="512" height="512">
  <SubTexture name="hit_effect_42260_6" width="164" height="164" cocos2d_pX="81.75" cocos2d_pY="81.75" x="166" y="166"/>
  <SubTexture name="hit_effect_42260_5" width="164" height="164" cocos2d_pX="81.75" cocos2d_pY="81.75" x="0" y="166"/>
  <SubTexture name="hit_effect_42260_4" width="164" height="164" cocos2d_pX="81.75" cocos2d_pY="81.75" x="0" y="0"/>
  <SubTexture name="hit_effect_42260_2" width="164" height="164" cocos2d_pX="81.75" cocos2d_pY="81.75" x="166" y="0"/>
  <SubTexture name="hit_effect_42260_1" width="164" height="164" cocos2d_pX="81.75" cocos2d_pY="81.75" x="332" y="0"/>
 </TextureAtlas>
</skeleton>